{"stac_version": "1.0.0-beta.2", "stac_extensions": [], "type": "Feature", "id": "cog_dhw_5km_faa9_2adb_2f09", "bbox": [180, -90, -180, 90], "geometry": {"type": "Polygon", "coordinates": [[[-180, -90], [-180, 90], [180, 90], [180, -90], [-180, -90]]]}, "properties": {"datetime": "2020-11-13T12:00:00Z", "start_datetime": "2020-11-13T12:00:00Z", "end_datetime": "2020-11-14T12:00:00Z"}, "links": [{"rel": "self", "href": "s3://covariate-ingest-data-dev/dhw/stac_items/cog_dhw_5km_faa9_2adb_2f09.json"}, {"rel": "collection", "href": "s3://covariate-ingest-data-dev/dhw/collection.json"}, {"rel": "parent", "href": "s3://covariate-ingest-data-dev/dhw/collection.json"}], "assets": {"image": {"href": "s3://covariate-ingest-data-dev/dhw/cogs/cog_dhw_5km_faa9_2adb_2f09.tif", "title": "dhw cog", "type": "geotiff"}, "thumbnail": {"href": "s3://covariate-ingest-data-dev/dhw/cogs/cog_dhw_5km_faa9_2adb_2f09.tif", "type": "geotiff", "title": "Thumbnail"}}}